Wysebee/__init__.py
Wysebee/cli/main.py
Wysebee/core/filesystem.py
Wysebee/core/resource_loader.py
Wysebee/core/singleton.py
Wysebee/core/temp_helper.py
Wysebee/core/wysebee.py
Wysebee/core/wysebee_backend.py
Wysebee/core/wysebee_webengine_page.py
Wysebee/core/wysebee_webpopup.py
Wysebee/core/wysebee_webview.py
wysebee-0.0.9.dist-info/entry_points.txt
wysebee-0.0.9.dist-info/WHEEL
wysebee-0.0.9.dist-info/METADATA
wysebee-0.0.9.dist-info/RECORD
