Metadata-Version: 2.4
Name: Wysebee
Version: 0.0.9
Summary: A simple cross-platform framework for your AI project.
Author-email: Jeff Xu <zxu@wysebee.com>
Requires-Python: >=3.9
License-Expression: MIT
Classifier: Programming Language :: Python :: 3
Classifier: Operating System :: OS Independent
Requires-Dist: pyside6>=6.9.0
Requires-Dist: Jinja2>=3.1.2
Requires-Dist: typer>=0.15.2
Requires-Dist: colorama>=0.4.6
Requires-Dist: watchdog==6.0.0
Project-URL: Homepage, https://github.com/wysebee/wysebee
Project-URL: Issues, https://github.com/wysebee/wysebee/issues
